README.rst
setup.py
bin/fl33t
fl33t/__init__.py
fl33t/client.py
fl33t/exceptions.py
fl33t/utils.py
fl33t.egg-info/PKG-INFO
fl33t.egg-info/SOURCES.txt
fl33t.egg-info/dependency_links.txt
fl33t.egg-info/requires.txt
fl33t.egg-info/top_level.txt
fl33t/cli/__init__.py
fl33t/cli/commands/builds.py
fl33t/cli/commands/devices.py
fl33t/cli/commands/fleets.py
fl33t/cli/commands/sessions.py
fl33t/cli/commands/trains.py
fl33t/models/__init__.py
fl33t/models/base.py
fl33t/models/build.py
fl33t/models/device.py
fl33t/models/fleet.py
fl33t/models/mixins.py
fl33t/models/session.py
fl33t/models/train.py