Metadata-Version: 1.2
Name: fl33t
Version: 0.6.1
Summary: Fl33t API Client
Home-page: https://github.com/fictivekin/fl33t-client
Author: Fictive Kin LLC
Author-email: hello@fictivekin.com
Maintainer: Fictive Kin LLC
Maintainer-email: hello@fictivekin.com
License: MIT
Platform: UNKNOWN
Classifier: Development Status :: 3 - Alpha
Classifier: License :: OSI Approved :: MIT License
Classifier: Programming Language :: Python :: 3.4
Classifier: Programming Language :: Python :: 3.5
Classifier: Programming Language :: Python :: 3.6
Classifier: Programming Language :: Python :: 3.7
Classifier: Topic :: Software Development
Requires-Python: >=3.4
